AUTHORS
LICENSE
README.md
setup.py
django_cubrid/__init__.py
django_cubrid/base.py
django_cubrid/client.py
django_cubrid/compiler.py
django_cubrid/creation.py
django_cubrid/features.py
django_cubrid/introspection.py
django_cubrid/operations.py
django_cubrid/schema.py
django_cubrid/validation.py
django_cubrid.egg-info/PKG-INFO
django_cubrid.egg-info/SOURCES.txt
django_cubrid.egg-info/dependency_links.txt
django_cubrid.egg-info/requires.txt
django_cubrid.egg-info/top_level.txt