Metadata-Version: 2.1
Name: django-cubrid
Version: 0.5.2
Summary: A Django database backend for CUBRID
Home-page: https://github.com/zimbrul-co/django_cubrid
Author: Casian Andrei
Author-email: casian@zco.ro
License: BSD-3-Clause
Classifier: Framework :: Django
Classifier: Programming Language :: Python :: 3
Classifier: License :: OSI Approved :: BSD License
Classifier: Operating System :: OS Independent
Requires-Python: >=3.9
License-File: LICENSE
License-File: AUTHORS
